transformio/__init__.py
transformio/accuracy.py
transformio/imwarp.py
transformio/transforms.py
transformio/utils.py
transformio/vector.py
transformio-0.1.0.dist-info/LICENSE
transformio-0.1.0.dist-info/METADATA
transformio-0.1.0.dist-info/WHEEL
transformio-0.1.0.dist-info/top_level.txt
transformio-0.1.0.dist-info/RECORD
